xcsf/sam.h
xcsf/neural_layer_noise.h
xcsf/neural_layer_args.c
xcsf/rule_dgp.c
xcsf/pybind_callback_checkpoint.h
xcsf/env.h
xcsf/param.c
xcsf/utils.h
xcsf/clset.c
xcsf/gp.c
xcsf/neural_layer_connected.c
xcsf/act_integer.c
xcsf/neural_layer_convolutional.c
xcsf/env_maze.h
xcsf/pred_constant.h
xcsf/pa.c
xcsf/cond_ternary.c
xcsf/CMakeLists.txt
xcsf/neural_layer_maxpool.c
xcsf/cond_gp.c
xcsf/cond_dgp.c
xcsf/pred_rls.h
xcsf/prediction.c
xcsf/condition.h
xcsf/neural_layer_upsample.h
xcsf/dgp.h
xcsf/cl.c
xcsf/config.h
xcsf/act_neural.h
xcsf/ea.h
xcsf/cond_neural.c
xcsf/pred_nlms.c
xcsf/perf.c
xcsf/xcsf.h
xcsf/neural_layer_recurrent.c
xcsf/xcs_supervised.c
xcsf/pred_neural.h
xcsf/neural_layer_avgpool.c
xcsf/cond_dummy.h
xcsf/env_mux.h
xcsf/rule_neural.h
xcsf/neural_layer_softmax.c
xcsf/cond_rectangle.c
xcsf/loss.c
xcsf/clset_neural.h
xcsf/__init__.py
xcsf/neural_layer_dropout.h
xcsf/env_csv.h
xcsf/neural_activations.h
xcsf/xcsf.cpython-314-darwin.so
xcsf/neural_layer_lstm.h
xcsf/image.c
xcsf/cond_ellipsoid.c
xcsf/xcs_rl.h
xcsf/neural_layer.h
xcsf/neural.c
xcsf/action.h
xcsf/blas.h
xcsf/pred_constant.c
xcsf/env_maze.c
xcsf/pa.h
xcsf/clset.h
xcsf/neural_layer_convolutional.h
xcsf/act_integer.h
xcsf/gp.h
xcsf/neural_layer_connected.h
xcsf/rule_dgp.h
xcsf/neural_layer_args.h
xcsf/utils.c
xcsf/env.c
xcsf/param.h
xcsf/main.c
xcsf/neural_layer_noise.c
xcsf/sam.c
xcsf/pybind_callback_earlystop.h
xcsf/pred_nlms.h
xcsf/cond_neural.h
xcsf/ea.c
xcsf/neural_layer_upsample.c
xcsf/condition.c
xcsf/act_neural.c
xcsf/config.c
xcsf/cl.h
xcsf/dgp.c
xcsf/pred_rls.c
xcsf/cond_dgp.h
xcsf/cond_gp.h
xcsf/prediction.h
xcsf/cond_ternary.h
xcsf/neural_layer_maxpool.h
xcsf/rule_neural.c
xcsf/env_mux.c
xcsf/pred_neural.c
xcsf/cond_dummy.c
xcsf/neural_layer_avgpool.h
xcsf/neural_layer_recurrent.h
xcsf/pybind_utils.h
xcsf/xcs_supervised.h
xcsf/pybind_wrapper.cpp
xcsf/perf.h
xcsf/xcsf.c
xcsf-1.4.10.dist-info/RECORD
xcsf-1.4.10.dist-info/WHEEL
xcsf-1.4.10.dist-info/top_level.txt
xcsf-1.4.10.dist-info/METADATA
xcsf-1.4.10.dist-info/licenses/LICENSE.md
