Metadata-Version: 2.4
Name: xcsf
Version: 1.4.10
Summary: XCSF learning classifier system: rule-based evolutionary machine learning
Maintainer-email: Richard Preen <rpreen@gmail.com>
License-Expression: GPL-3.0-or-later
Project-URL: Homepage, https://github.com/xcsf-dev/xcsf
Project-URL: Changelog, https://github.com/xcsf-dev/xcsf/CHANGELOG.md
Project-URL: Documentation, https://github.com/xcsf-dev/xcsf/wiki
Project-URL: Bug Tracker, https://github.com/xcsf-dev/xcsf/issues
Project-URL: Discussions, https://github.com/xcsf-dev/xcsf/discussions
Keywords: divide and conquer,evolutionary algorithm,genetic programming,learning classifier system,least squares,machine learning,neural networks,neuroevolution,reinforcement learning,rule-based,supervised learning,stochastic gradient descent,XCS,XCSF 
Classifier: Development Status :: 5 - Production/Stable
Classifier: Intended Audience :: Developers
Classifier: Intended Audience :: Science/Research
Classifier: Programming Language :: C
Classifier: Programming Language :: C++
Classifier: Programming Language :: Python :: 3.9
Classifier: Programming Language :: Python :: 3.10
Classifier: Programming Language :: Python :: 3.11
Classifier: Programming Language :: Python :: 3.12
Classifier: Programming Language :: Python :: 3.13
Classifier: Programming Language :: Python :: 3.14
Classifier: Topic :: Scientific/Engineering
Classifier: Topic :: Scientific/Engineering :: Artificial Intelligence
Classifier: Operating System :: POSIX :: Linux
Classifier: Operating System :: MacOS :: MacOS X
Classifier: Operating System :: Microsoft :: Windows :: Windows 10
Classifier: Operating System :: Microsoft :: Windows :: Windows 11
Requires-Python: >=3.9
License-File: LICENSE.md
Dynamic: license-file
